{
  "id": "population-pyramids",
  "title": "人口ピラミッド読解（上級）",
  "description": "年齢構成から医療・福祉・雇用を推論",
  "cards": [
    { "front": "底が広く頂部が細い『富士山型』が示す段階", "back": "多産多死→多産少死への移行期（若年人口が多い）", "hint": "高出生率" },
    { "front": "釣鐘型の含意", "back": "出生率安定で人口ほぼ横ばい・高齢化進行", "hint": "先進国型" },
    { "front": "つぼ型の政策課題", "back": "少子化対策・労働力確保・移民受け入れ", "hint": "超少子化" },
    { "front": "20–39歳で男性が過剰に見える要因", "back": "建設・鉱業など男性就業の流入／外国人労働者", "hint": "産業構造" },
    { "front": "農村地域で高齢女性が突出する理由", "back": "長寿化＋若年女性の都市流出", "hint": "社会移動" },
    { "front": "ベビーブームの『こぶ』が移動すると？", "back": "医療・教育・年金など需要の山が時系列に移動", "hint": "コーホート効果" }
  ]
}
